AutoItLibrary/__init__.py
AutoItLibrary3/__init__.py
RobotFramework/Extensions/AutoItLibrary/Au3Info.exe
RobotFramework/Extensions/AutoItLibrary/AutoItLibrary.html
RobotFramework/Extensions/AutoItLibrary/AutoItX.chm
RobotFramework/Extensions/AutoItLibrary/AutoItX3.dll
RobotFramework/Extensions/AutoItLibrary/AutoIt_License.html
RobotFramework/Extensions/AutoItLibrary/COPYRIGHT.txt
RobotFramework/Extensions/AutoItLibrary/LICENSE.txt
RobotFramework/Extensions/AutoItLibrary/ReadMe.txt
RobotFramework/Extensions/AutoItLibrary/tests/CalculatorGUIMap.py
RobotFramework/Extensions/AutoItLibrary/tests/Calculator_Test_Cases.html
RobotFramework/Extensions/AutoItLibrary/tests/RobotIDE.bat
RobotFramework/Extensions/AutoItLibrary/tests/RunTests.bat
RobotFramework/Extensions/AutoItLibrary/tests/__init__.html
AutoItLibrary3-1.1.post1.dist-info/LICENSE.txt
AutoItLibrary3-1.1.post1.dist-info/METADATA
AutoItLibrary3-1.1.post1.dist-info/WHEEL
AutoItLibrary3-1.1.post1.dist-info/top_level.txt
AutoItLibrary3-1.1.post1.dist-info/RECORD
