Metadata-Version: 2.1
Name: AutoItLibrary3
Version: 1.1.post1
Summary: AutoItLibrary for Robot Framework
Home-page: http://code.google.com/p/robotframework-autoitlibrary/
Author: Martin Taylor
Author-email: cmtaylor@ti.com
License: Apache License 2.0
Platform: Microsoft Windows
Classifier: Development Status :: 5 - Production/Stable
Classifier: License :: OSI Approved :: Apache Software License
Classifier: Operating System :: Microsoft :: Windows
Classifier: Programming Language :: Python
Classifier: Topic :: Software Development :: Testing
